nameko/__init__.py
nameko/__main__.py
nameko/constants.py
nameko/containers.py
nameko/contextdata.py
nameko/dependency_providers.py
nameko/events.py
nameko/exceptions.py
nameko/extensions.py
nameko/log_helpers.py
nameko/messaging.py
nameko/rpc.py
nameko/runners.py
nameko/serialization.py
nameko/timer.py
nameko/amqp/__init__.py
nameko/amqp/publish.py
nameko/cli/__init__.py
nameko/cli/actions.py
nameko/cli/backdoor.py
nameko/cli/code.py
nameko/cli/commands.py
nameko/cli/main.py
nameko/cli/run.py
nameko/cli/shell.py
nameko/cli/show_config.py
nameko/standalone/__init__.py
nameko/standalone/events.py
nameko/standalone/rpc.py
nameko/testing/__init__.py
nameko/testing/pytest.py
nameko/testing/rabbit.py
nameko/testing/services.py
nameko/testing/utils.py
nameko/testing/waiting.py
nameko/testing/websocket.py
nameko/utils/__init__.py
nameko/utils/retry.py
nameko/utils/concurrency/__init__.py
nameko/web/__init__.py
nameko/web/handlers.py
nameko/web/server.py
nameko/web/websocket.py
nameko-2.14.1.dist-info/LICENSE.txt
nameko-2.14.1.dist-info/METADATA
nameko-2.14.1.dist-info/NOTICE.txt
nameko-2.14.1.dist-info/WHEEL
nameko-2.14.1.dist-info/entry_points.txt
nameko-2.14.1.dist-info/top_level.txt
nameko-2.14.1.dist-info/zip-safe
nameko-2.14.1.dist-info/RECORD
